LICENSE
MANIFEST.in
README.rst
setup.cfg
setup.py
hidash/__init__.py
hidash/admin.py
hidash/forms.py
hidash/models.py
hidash/router.py
hidash/views.py
hidash.egg-info/PKG-INFO
hidash.egg-info/SOURCES.txt
hidash.egg-info/dependency_links.txt
hidash.egg-info/requires.txt
hidash.egg-info/top_level.txt
hidash/migrations/0001_initial.py
hidash/migrations/0002_auto_20160929_1312.py
hidash/migrations/0003_auto_20161005_0715.py
hidash/migrations/0004_auto_20161012_0739.py
hidash/migrations/0005_auto_20161213_1214.py
hidash/migrations/0006_auto_20161213_1238.py
hidash/migrations/0007_auto_20170206_1206.py
hidash/migrations/__init__.py
hidash/south_migrations/0001_initial.py
hidash/south_migrations/0002_auto__del_chartgroup.py
hidash/south_migrations/0003_auto__add_group__add_chartgroup__add_chartparameter__add_field_chart_s.py
hidash/south_migrations/0004_auto__add_field_scheduledreport_email_subject__add_field_scheduledrepo.py
hidash/south_migrations/0005_auto__add_field_scheduledreportparam_is_parameter_value_sql_function.py
hidash/south_migrations/0006_auto__add_field_scheduledreport_group__add_field_scheduledreport_templ.py
hidash/south_migrations/0007_auto__chg_field_chart_name__chg_field_chart_height__chg_field_chart_di.py
hidash/south_migrations/0008_auto__add_field_group_template.py
hidash/south_migrations/__init__.py
hidash/static/css/font-awesome.min.css
hidash/static/css/reports.css
hidash/static/css/reports.css~
hidash/static/fonts/FontAwesome.otf
hidash/static/fonts/fontawesome-webfont.eot
hidash/static/fonts/fontawesome-webfont.svg
hidash/static/fonts/fontawesome-webfont.ttf
hidash/static/fonts/fontawesome-webfont.woff
hidash/static/fonts/fontawesome-webfont.woff2
hidash/static/js/hidash-app.js
hidash/static/js/hidash-app.js~
hidash/static/js/reports-hidash.js
hidash/static/js/reports-hidash.js~
hidash/static/libs/exporting.min.js
hidash/static/libs/highcharts.min.js
hidash/static/libs/jquery.min.js
hidash/static/libs/pace.js
hidash/static/libs/ui-bootstrap-tpls-0.9.0.min.js
hidash/static/libs/angular/.bower.json
hidash/static/libs/angular/README.md
hidash/static/libs/angular/angular-csp.css
