Metadata-Version: 1.1
Name: hidash
Version: 0.2.29
Summary: A Django app to generate google charts, excel and pdf straight from the database.
Home-page: UNKNOWN
Author: Devashish Sharma , Swapnil Tiwari
Author-email: devashishsharma2302@gmail.com , swapniltiwari43@gmail.com
License: MIT
Keywords: Chart,reports,Export,django,dashboard,google charts,excel,pdf
Platform: UNKNOWN
Classifier: Environment :: Web Environment
Classifier: Framework :: Django
Classifier: Intended Audience :: Developers
Classifier: License :: OSI Approved :: MIT License
Classifier: Operating System :: OS Independent
Classifier: Programming Language :: Python
Classifier: Topic :: Internet :: WWW/HTTP
Classifier: Topic :: Internet :: WWW/HTTP :: Dynamic Content
